{"status":"done","publicPath":"http://0.0.0.0:8080/","chunks":{"app":[{"name":"bundle.js","publicPath":"http://0.0.0.0:8080/bundle.js","path":"/Users/maks_p/Courses/quora-clone/quoraclone/frontend/dist/bundle.js"},{"name":"app.d8f2e3245903a169a09e.hot-update.js","publicPath":"http://0.0.0.0:8080/app.d8f2e3245903a169a09e.hot-update.js","path":"/Users/maks_p/Courses/quora-clone/quoraclone/frontend/dist/app.d8f2e3245903a169a09e.hot-update.js"}]},"error":"ModuleError","message":"Module Error (from ./node_modules/eslint-loader/index.js):\n\n/Users/maks_p/Courses/quora-clone/quoraclone/frontend/src/views/Question.vue\n  4:39  error    Parsing error: x-invalid-end-tag                                                                                                                                                                                      vue/no-parsing-error\n  4:40  warning  Parsing error: Unexpected closing tag \"h2\". It may happen when the tag has already been closed by another tag. For more info see https://www.w3.org/TR/html5/syntax.html#closing-elements-that-have-implied-end-tags  prettier/prettier\n\n✖ 2 problems (1 error, 1 warning)\n"}